expandLHS/__init__.py
expandLHS/__version__.py
expandLHS/expandLHS.py
expandlhs-1.1.0.dist-info/licenses/LICENSE
expandlhs-1.1.0.dist-info/METADATA
expandlhs-1.1.0.dist-info/WHEEL
expandlhs-1.1.0.dist-info/top_level.txt
expandlhs-1.1.0.dist-info/RECORD
