Metadata-Version: 2.4
Name: expandLHS
Version: 1.1.0
Summary: A Python package to expand a Latin Hypercube Sample
Home-page: https://github.com/m-boschini/expandLHS
Author: Matteo Boschini, Davide Gerosa
Author-email: Matteo Boschini <m.boschini1@campus.unimib.it>, Davide Gerosa <davide.gerosa@unimib.it>
License: Copyright (c) 2025 Matteo Boschini
Project-URL: Homepage, https://github.com/m-boschini/expandLHS
Project-URL: Documentation, https://m-boschini.github.io/expandLHS/
Requires-Python: >=3.7
License-File: LICENSE
Requires-Dist: numpy
Requires-Dist: scipy
Requires-Dist: numba>=0.57
Dynamic: author
Dynamic: home-page
Dynamic: license-file
Dynamic: requires-python
